README.txt
setup.py
xodb/__init__.py
xodb/database.py
xodb/elements.py
xodb/exc.py
xodb/memo.py
xodb/search.py
xodb/xaql.py
xodb.egg-info/PKG-INFO
xodb.egg-info/SOURCES.txt
xodb.egg-info/dependency_links.txt
xodb.egg-info/requires.txt
xodb.egg-info/top_level.txt
xodb/net/__init__.py
xodb/net/broker.py
xodb/net/client.py
xodb/net/events.py
xodb/net/read_broker.py
xodb/net/reader.py
xodb/net/worker.py
xodb/net/write_broker.py
xodb/net/writer.py
xodb/snowball/__init__.py
xodb/snowball/english/__init__.py
xodb/snowball/french/__init__.py
xodb/snowball/german/__init__.py
xodb/snowball/italian/__init__.py
xodb/snowball/russian/__init__.py
xodb/snowball/spanish/__init__.py
xodb/tools/__init__.py
xodb/tools/geoprint.py
xodb/tools/rpc.py
xodb/tools/signals.py