Metadata-Version: 1.1
Name: xodb
Version: 0.6.2
Summary: experimental xapian object database
Home-page: https://github.com/michelp/xodb
Author: Michel Pelletier - Action Without Borders
Author-email: michel@idealist.org
License: MIT License
Platform: UNKNOWN
Classifier: Development Status :: 3 - Alpha
Classifier: Intended Audience :: Developers
Classifier: License :: OSI Approved :: MIT License
Classifier: Operating System :: OS Independent
Classifier: Programming Language :: Python
Classifier: Programming Language :: Python :: 2.5
Classifier: Programming Language :: Python :: 2.6
